reltc/__init__.py
reltc/main.py
reltc-1.1.1.dist-info/METADATA
reltc-1.1.1.dist-info/WHEEL
reltc-1.1.1.dist-info/entry_points.txt
reltc-1.1.1.dist-info/top_level.txt
reltc-1.1.1.dist-info/RECORD
