Metadata-Version: 2.4
Name: reltc
Version: 1.1.1
Summary: Linux TC command-generator
Home-page: https://github.com/mon231/reltc/
Author: Ariel Tubul
Requires-Dist: PyQt5
Dynamic: author
Dynamic: description
Dynamic: description-content-type
Dynamic: home-page
Dynamic: requires-dist
Dynamic: summary
